basecollab-0.1.4.dist-info/METADATA
basecollab-0.1.4.dist-info/WHEEL
basecollab.libs/libcrypto-27a68367.so.3
basecollab.libs/libssl-0ee20961.so.3
basecollab.libs/libzstd-27f07c9a.so.1
basecollab/__init__.py
basecollab/basecollab.cpython-311-x86_64-linux-gnu.so
basecollab-0.1.4.dist-info/RECORD
