Metadata-Version: 2.4
Name: basecollab
Version: 0.1.4
Classifier: Programming Language :: Python
Classifier: Programming Language :: Python :: 3
Classifier: Programming Language :: Python :: 3 :: Only
Classifier: Programming Language :: Rust
Classifier: License :: OSI Approved :: MIT License
Classifier: Operating System :: POSIX :: Linux
Classifier: Operating System :: MacOS
Summary: Powerful Rust package that parse codebase to extract relevant metadatas in tree structure.
Author: ccouble
License: MIT
Requires-Python: >=3.8
Project-URL: Homepage, https://www.basecollab.com
